bolditalic/__init__.py
bolditalic/bolditalic.css
bolditalic-0.1.4.dist-info/DESCRIPTION.rst
bolditalic-0.1.4.dist-info/METADATA
bolditalic-0.1.4.dist-info/RECORD
bolditalic-0.1.4.dist-info/WHEEL
bolditalic-0.1.4.dist-info/metadata.json
bolditalic-0.1.4.dist-info/top_level.txt
