Metadata-Version: 2.0
Name: bolditalic
Version: 0.1.4
Summary: **DEPRECATED** A Sphinx extension that enables inline bold + italic.
Home-page: https://github.com/kallimachos/bolditalic
Author: Brian moss
Author-email: kallimachos@gmail.com
License: GPLv3
Keywords: sphinx documentation bold italic
Platform: UNKNOWN
Classifier: Development Status :: 4 - Beta
Classifier: Intended Audience :: Developers
Classifier: Topic :: Documentation :: Sphinx
Classifier: Framework :: Sphinx :: Extension
Classifier: License :: OSI Approved :: GNU General Public License v3 (GPLv3)
Classifier: Programming Language :: Python :: 2
Classifier: Programming Language :: Python :: 2.7
Classifier: Programming Language :: Python :: 3
Classifier: Programming Language :: Python :: 3.4
